{
  "timestamp": "2025-07-19T23:18:24.115512",
  "services": {
    "dspy_service": {
      "name": "dspy_service",
      "url": "http://localhost:8001",
      "status": "healthy",
      "response_time": 0.002742767333984375,
      "last_check": "2025-07-19 23:18:20.406960",
      "error_count": 0,
      "success_count": 80,
      "uptime_percentage": 100.0,
      "last_error": null
    },
    "backend_api": {
      "name": "backend_api",
      "url": "http://localhost:5000",
      "status": "healthy",
      "response_time": 0.0016055107116699219,
      "last_check": "2025-07-19 23:18:20.408596",
      "error_count": 0,
      "success_count": 80,
      "uptime_percentage": 100.0,
      "last_error": null
    },
    "frontend": {
      "name": "frontend",
      "url": "http://localhost:3000",
      "status": "healthy",
      "response_time": 0.0026521682739257812,
      "last_check": "2025-07-19 23:18:20.411280",
      "error_count": 0,
      "success_count": 80,
      "uptime_percentage": 100.0,
      "last_error": null
    }
  },
  "system": {
    "cpu_usage": 16.0,
    "memory_usage": 48.2,
    "disk_usage": 71.5,
    "network_io": {
      "bytes_sent": 167406125,
      "bytes_recv": 1610352278
    },
    "timestamp": "2025-07-19 23:18:21.411918"
  },
  "workflows": [
    {
      "workflow_name": "end_to_end_user_interaction",
      "total_time": 1.785513162612915,
      "steps": [
        {
          "name": "dspy_direct_test",
          "duration": 0.8787448406219482,
          "success": true,
          "details": "Status: 200"
        },
        {
          "name": "backend_api_test",
          "duration": 0.9066674709320068,
          "success": true,
          "details": "Status: 200, Enhanced: False"
        },
        {
          "name": "educational_quality_check",
          "duration": 5.245208740234375e-06,
          "success": false,
          "details": "Educational structure detected: False"
        }
      ],
      "success": false,
      "timestamp": "2025-07-19 23:15:34.739855",
      "error_message": null
    },
    {
      "workflow_name": "end_to_end_user_interaction",
      "total_time": 1.8363721370697021,
      "steps": [
        {
          "name": "dspy_direct_test",
          "duration": 0.904780387878418,
          "success": true,
          "details": "Status: 200"
        },
        {
          "name": "backend_api_test",
          "duration": 0.9314939975738525,
          "success": true,
          "details": "Status: 200, Enhanced: False"
        },
        {
          "name": "educational_quality_check",
          "duration": 4.5299530029296875e-06,
          "success": false,
          "details": "Educational structure detected: False"
        }
      ],
      "success": false,
      "timestamp": "2025-07-19 23:15:53.466050",
      "error_message": null
    },
    {
      "workflow_name": "end_to_end_user_interaction",
      "total_time": 1.7943260669708252,
      "steps": [
        {
          "name": "dspy_direct_test",
          "duration": 0.898604154586792,
          "success": true,
          "details": "Status: 200"
        },
        {
          "name": "backend_api_test",
          "duration": 0.8956255912780762,
          "success": true,
          "details": "Status: 200, Enhanced: False"
        },
        {
          "name": "educational_quality_check",
          "duration": 5.245208740234375e-06,
          "success": false,
          "details": "Educational structure detected: False"
        }
      ],
      "success": false,
      "timestamp": "2025-07-19 23:16:12.213322",
      "error_message": null
    },
    {
      "workflow_name": "end_to_end_user_interaction",
      "total_time": 1.7793056964874268,
      "steps": [
        {
          "name": "dspy_direct_test",
          "duration": 0.8859822750091553,
          "success": true,
          "details": "Status: 200"
        },
        {
          "name": "backend_api_test",
          "duration": 0.8932242393493652,
          "success": true,
          "details": "Status: 200, Enhanced: False"
        },
        {
          "name": "educational_quality_check",
          "duration": 4.5299530029296875e-06,
          "success": false,
          "details": "Educational structure detected: False"
        }
      ],
      "success": false,
      "timestamp": "2025-07-19 23:16:30.879659",
      "error_message": null
    },
    {
      "workflow_name": "end_to_end_user_interaction",
      "total_time": 1.7982110977172852,
      "steps": [
        {
          "name": "dspy_direct_test",
          "duration": 0.8990094661712646,
          "success": true,
          "details": "Status: 200"
        },
        {
          "name": "backend_api_test",
          "duration": 0.8989541530609131,
          "success": true,
          "details": "Status: 200, Enhanced: False"
        },
        {
          "name": "educational_quality_check",
          "duration": 4.76837158203125e-06,
          "success": false,
          "details": "Educational structure detected: False"
        }
      ],
      "success": false,
      "timestamp": "2025-07-19 23:16:49.570906",
      "error_message": null
    },
    {
      "workflow_name": "end_to_end_user_interaction",
      "total_time": 1.840287446975708,
      "steps": [
        {
          "name": "dspy_direct_test",
          "duration": 0.9009323120117188,
          "success": true,
          "details": "Status: 200"
        },
        {
          "name": "backend_api_test",
          "duration": 0.9392580986022949,
          "success": true,
          "details": "Status: 200, Enhanced: False"
        },
        {
          "name": "educational_quality_check",
          "duration": 4.76837158203125e-06,
          "success": false,
          "details": "Educational structure detected: False"
        }
      ],
      "success": false,
      "timestamp": "2025-07-19 23:17:08.298963",
      "error_message": null
    },
    {
      "workflow_name": "end_to_end_user_interaction",
      "total_time": 1.793804407119751,
      "steps": [
        {
          "name": "dspy_direct_test",
          "duration": 0.8982856273651123,
          "success": true,
          "details": "Status: 200"
        },
        {
          "name": "backend_api_test",
          "duration": 0.8953948020935059,
          "success": true,
          "details": "Status: 200, Enhanced: False"
        },
        {
          "name": "educational_quality_check",
          "duration": 4.76837158203125e-06,
          "success": false,
          "details": "Educational structure detected: False"
        }
      ],
      "success": false,
      "timestamp": "2025-07-19 23:17:27.044771",
      "error_message": null
    },
    {
      "workflow_name": "end_to_end_user_interaction",
      "total_time": 1.7804269790649414,
      "steps": [
        {
          "name": "dspy_direct_test",
          "duration": 0.9086191654205322,
          "success": true,
          "details": "Status: 200"
        },
        {
          "name": "backend_api_test",
          "duration": 0.8717069625854492,
          "success": true,
          "details": "Status: 200, Enhanced: False"
        },
        {
          "name": "educational_quality_check",
          "duration": 4.291534423828125e-06,
          "success": false,
          "details": "Educational structure detected: False"
        }
      ],
      "success": false,
      "timestamp": "2025-07-19 23:17:45.732112",
      "error_message": null
    },
    {
      "workflow_name": "end_to_end_user_interaction",
      "total_time": 1.7747139930725098,
      "steps": [
        {
          "name": "dspy_direct_test",
          "duration": 0.8770163059234619,
          "success": true,
          "details": "Status: 200"
        },
        {
          "name": "backend_api_test",
          "duration": 0.8975651264190674,
          "success": true,
          "details": "Status: 200, Enhanced: False"
        },
        {
          "name": "educational_quality_check",
          "duration": 6.4373016357421875e-06,
          "success": false,
          "details": "Educational structure detected: False"
        }
      ],
      "success": false,
      "timestamp": "2025-07-19 23:18:04.457784",
      "error_message": null
    },
    {
      "workflow_name": "end_to_end_user_interaction",
      "total_time": 1.8170576095581055,
      "steps": [
        {
          "name": "dspy_direct_test",
          "duration": 0.9271833896636963,
          "success": true,
          "details": "Status: 200"
        },
        {
          "name": "backend_api_test",
          "duration": 0.8897626399993896,
          "success": true,
          "details": "Status: 200, Enhanced: False"
        },
        {
          "name": "educational_quality_check",
          "duration": 5.9604644775390625e-06,
          "success": false,
          "details": "Educational structure detected: False"
        }
      ],
      "success": false,
      "timestamp": "2025-07-19 23:18:23.228993",
      "error_message": null
    }
  ],
  "summary": {
    "overall_health": "healthy",
    "services_up": 3,
    "services_total": 3,
    "average_response_time": 0.002333482106526693,
    "workflow_success_rate": 0.0
  }
}